neutron_fwaas_dashboard/__init__.py
neutron_fwaas_dashboard/version.py
neutron_fwaas_dashboard/api/__init__.py
neutron_fwaas_dashboard/api/fwaas_v2.py
neutron_fwaas_dashboard/dashboards/__init__.py
neutron_fwaas_dashboard/dashboards/project/__init__.py
neutron_fwaas_dashboard/dashboards/project/firewalls_v2/__init__.py
neutron_fwaas_dashboard/dashboards/project/firewalls_v2/forms.py
neutron_fwaas_dashboard/dashboards/project/firewalls_v2/panel.py
neutron_fwaas_dashboard/dashboards/project/firewalls_v2/tables.py
neutron_fwaas_dashboard/dashboards/project/firewalls_v2/tabs.py
neutron_fwaas_dashboard/dashboards/project/firewalls_v2/tests.py
neutron_fwaas_dashboard/dashboards/project/firewalls_v2/urls.py
neutron_fwaas_dashboard/dashboards/project/firewalls_v2/views.py
neutron_fwaas_dashboard/dashboards/project/firewalls_v2/widgets.py
neutron_fwaas_dashboard/dashboards/project/firewalls_v2/workflows.py
neutron_fwaas_dashboard/dashboards/project/firewalls_v2/templates/firewalls_v2/_addport.html
neutron_fwaas_dashboard/dashboards/project/firewalls_v2/templates/firewalls_v2/_firewallgroup_details.html
neutron_fwaas_dashboard/dashboards/project/firewalls_v2/templates/firewalls_v2/_insert_rule_to_policy.html
neutron_fwaas_dashboard/dashboards/project/firewalls_v2/templates/firewalls_v2/_policy_details.html
neutron_fwaas_dashboard/dashboards/project/firewalls_v2/templates/firewalls_v2/_remove_rule_from_policy.html
neutron_fwaas_dashboard/dashboards/project/firewalls_v2/templates/firewalls_v2/_removeport.html
neutron_fwaas_dashboard/dashboards/project/firewalls_v2/templates/firewalls_v2/_rule_details.html
neutron_fwaas_dashboard/dashboards/project/firewalls_v2/templates/firewalls_v2/_update_port_help.html
neutron_fwaas_dashboard/dashboards/project/firewalls_v2/templates/firewalls_v2/_update_ports.html
neutron_fwaas_dashboard/dashboards/project/firewalls_v2/templates/firewalls_v2/_update_rule_help.html
neutron_fwaas_dashboard-10.0.0.dist-info/AUTHORS
neutron_fwaas_dashboard-10.0.0.dist-info/LICENSE
neutron_fwaas_dashboard-10.0.0.dist-info/METADATA
neutron_fwaas_dashboard-10.0.0.dist-info/WHEEL
neutron_fwaas_dashboard-10.0.0.dist-info/pbr.json
neutron_fwaas_dashboard-10.0.0.dist-info/top_level.txt
neutron_fwaas_dashboard-10.0.0.dist-info/RECORD
